flask_siilo.py
flask_siilo-0.1.2.dist-info/DESCRIPTION.rst
flask_siilo-0.1.2.dist-info/METADATA
flask_siilo-0.1.2.dist-info/metadata.json
flask_siilo-0.1.2.dist-info/RECORD
flask_siilo-0.1.2.dist-info/top_level.txt
flask_siilo-0.1.2.dist-info/WHEEL
