Metadata-Version: 2.0
Name: flask-siilo
Version: 0.1.2
Summary: A simple storage for Flask based on siilo.
Home-page: https://github.com/s-m-i-t-a/flask_siilo
Author: Jindřich Smitka
Author-email: smitka.j@gmail.com
License: BSD
Keywords: flask_siilo
Platform: UNKNOWN
Classifier: Development Status :: 2 - Pre-Alpha
Classifier: Intended Audience :: Developers
Classifier: License :: OSI Approved :: BSD License
Classifier: Natural Language :: English
Classifier: Programming Language :: Python :: 2
Classifier: Programming Language :: Python :: 2.7
Classifier: Programming Language :: Python :: 3
Classifier: Programming Language :: Python :: 3.3
Classifier: Programming Language :: Python :: 3.4
Requires-Dist: wheel (==0.24.0)
Requires-Dist: Flask (>=0.10.1)
Requires-Dist: six (>=1.7.3)
Requires-Dist: apache-libcloud
Requires-Dist: siilo (==0.1.0)
